{
    "name": "pray",
    "author": "MrSypz",
    "description": "description",
    "emote": {
        "beginTick": 0,
        "endTick": 10,
        "stopTick": 201,
        "isLoop": true,
        "returnTick": 10,
        "degrees": false,
        "moves": [
            {
                "tick": 10,
                "easing": "OUTQUART",
                "turn": 0,
                "head": {
                    "pitch": 0.436
                },
                "rightArm": {
                    "pitch": -1.047,
                    "yaw": -0.349,
                    "axis": 0.262
                },
                "leftArm": {
                    "pitch": -1.047,
                    "yaw": 0.349,
                    "axis": -0.262
                }
            }
        ]
    }
}